README.md
setup.py
Pyiiko/__init__.py
Pyiiko/biz.py
Pyiiko/card5.py
Pyiiko/frontWeb.py
Pyiiko/server.py
Pyiiko/settings.py
Pyiiko/transport.py
Pyiiko/webAPI.py
Pyiiko.egg-info/PKG-INFO
Pyiiko.egg-info/SOURCES.txt
Pyiiko.egg-info/dependency_links.txt
Pyiiko.egg-info/requires.txt
Pyiiko.egg-info/top_level.txt
test/__init__.py
test/test.py
test/test_server.py
test/test_transport.py