Metadata-Version: 1.0
Name: Pyiiko
Version: 0.2.11
Summary: Library for iikoAPI
Home-page: https://github.com/gadzhi/pyiiko
Author: Gadzhibala Pirmagomedov
Author-email: gadzhibala@protonmail.com
License: UNKNOWN
Platform: UNKNOWN
